firstpackage/__init__.py
firstpackage/helloworld.py
mypackage_jim_plzdont-0.0.3.dist-info/LICENSE.txt
mypackage_jim_plzdont-0.0.3.dist-info/METADATA
mypackage_jim_plzdont-0.0.3.dist-info/WHEEL
mypackage_jim_plzdont-0.0.3.dist-info/top_level.txt
mypackage_jim_plzdont-0.0.3.dist-info/RECORD
