Metadata-Version: 2.1
Name: mypackage-jim-plzdont
Version: 0.0.3
Summary: Say hello!
Home-page: https://gitlab.com/dmpapazog/mypackage_jim_plzdont
Author: Jim Pap
Author-email: dmpapazog@gmail.com
License: MIT License
Platform: UNKNOWN
Classifier: Programming Language :: Python :: 3
Classifier: Programming Language :: Python :: 3.6
Classifier: Programming Language :: Python :: 3.7
Classifier: License :: OSI Approved :: MIT License
Classifier: Operating System :: OS Independent
License-File: LICENSE.txt
Provides-Extra: dev
Requires-Dist: pytest (>=3.7) ; extra == 'dev'
Requires-Dist: pytest-cov ; extra == 'dev'
Requires-Dist: check-manifest ; extra == 'dev'
Requires-Dist: tox ; extra == 'dev'
